{
	"archive" : {},
	"artifacts" : 
	[
		{
			"path" : "include/libcryptography.a"
		}
	],
	"backtrace" : 1,
	"backtraceGraph" : 
	{
		"commands" : 
		[
			"add_library"
		],
		"files" : 
		[
			"include/CMakeLists.txt"
		],
		"nodes" : 
		[
			{
				"file" : 0
			},
			{
				"command" : 0,
				"file" : 0,
				"line" : 3,
				"parent" : 0
			}
		]
	},
	"compileGroups" : 
	[
		{
			"compileCommandFragments" : 
			[
				{
					"fragment" : "-O3 -DNDEBUG"
				}
			],
			"language" : "CXX",
			"sourceIndexes" : 
			[
				0,
				1,
				2,
				3,
				4,
				5
			]
		}
	],
	"id" : "cryptography::@14b3099d61bfdbeae804",
	"name" : "cryptography",
	"nameOnDisk" : "libcryptography.a",
	"paths" : 
	{
		"build" : "include",
		"source" : "include"
	},
	"sourceGroups" : 
	[
		{
			"name" : "Source Files",
			"sourceIndexes" : 
			[
				0,
				1,
				2,
				3,
				4,
				5
			]
		}
	],
	"sources" : 
	[
		{
			"backtrace" : 1,
			"compileGroupIndex" : 0,
			"path" : "include/caesar.cpp",
			"sourceGroupIndex" : 0
		},
		{
			"backtrace" : 1,
			"compileGroupIndex" : 0,
			"path" : "include/menu.cpp",
			"sourceGroupIndex" : 0
		},
		{
			"backtrace" : 1,
			"compileGroupIndex" : 0,
			"path" : "include/playfair.cpp",
			"sourceGroupIndex" : 0
		},
		{
			"backtrace" : 1,
			"compileGroupIndex" : 0,
			"path" : "include/public.cpp",
			"sourceGroupIndex" : 0
		},
		{
			"backtrace" : 1,
			"compileGroupIndex" : 0,
			"path" : "include/vernam.cpp",
			"sourceGroupIndex" : 0
		},
		{
			"backtrace" : 1,
			"compileGroupIndex" : 0,
			"path" : "include/vigenere.cpp",
			"sourceGroupIndex" : 0
		}
	],
	"type" : "STATIC_LIBRARY"
}
